sem3/DSDL-LAB/Lab-02/Q2/q1/part1/and_or.v
module and_or(a,b,c,lhs,rhs);
    input a,b,c;
    output lhs,rhs;
    assign lhs = (a|(b&c))&(b|(c&a));
    assign rhs = (a&b)|(b&c)|(c&a);
endmodule

sem3/DSDL-LAB/Lab-02/Q2/q1/part1/and_or_tb.v
`timescale 1ns/1ns
`include "and_or.v" 

module and_or_tb();
reg a,b,c;
wire lhs,rhs;
and_or andor(a,b,c,lhs,rhs); 
initial
begin
$dumpfile("and_or_tb.vcd");
$dumpvars(0, and_or_tb);

a=1'b0; b=1'b0; c=1'b0;
#20;
a=1'b0; b=1'b0; c=1'b1;
#20;
a=1'b0; b=1'b1; c=1'b0;
#20;
a=1'b0; b=1'b1; c=1'b1;
#20;
a=1'b1; b=1'b0; c=1'b0;
#20;
a=1'b1; b=1'b0; c=1'b1;
#20;
a=1'b1; b=1'b1; c=1'b0;
#20;
a=1'b1; b=1'b1; c=1'b1;
#20;



$display("Test complete");
end
endmodule

sem3/DSDL-LAB/Lab-02/Q2/q1/part1/and_or_tb.vcd
$date
	Sat Sep  3 15:18:50 2022
$end
$version
	Icarus Verilog
$end
$timescale
	1ns
$end
$scope module and_or_tb $end
$var wire 1 ! rhs $end
$var wire 1 " lhs $end
$var reg 1 # a $end
$var reg 1 $ b $end
$var reg 1 % c $end
$scope module andor $end
$var wire 1 # a $end
$var wire 1 $ b $end
$var wire 1 % c $end
$var wire 1 " lhs $end
$var wire 1 ! rhs $end
$upscope $end
$upscope $end
$enddefinitions $end
#0
$dumpvars
0%
0$
0#
0"
0!
$end
#20
1%
#40
0%
1$
#60
1"
1!
1%
#80
0!
0"
0%
0$
1#
#100
1"
1!
1%
#120
0%
1$
#140
1%
