sem3/DSDL-LAB/Lab-06/q1.v
module q1(W,F);
    input [3:0]W;
    // input En;
    // output [15:0]Y;
    output F;
    wire [0:15]Y;
    dec4to16 dec(W,Y);
    assign F = Y[1] | Y[3] | Y[6] | Y[7] | Y[9] | Y[14] | Y[15];
endmodule

module dec4to16(W,Y);
    input [3:0]W;
    // input En;
    output [15:0]Y;
    reg [15:0]Y;
    always@(W)
    begin
        // if(En==0)
            // Y=16'b0000000000000000;
        // else
            case(W)
                0:Y=16'b1000000000000000;
                1:Y=16'b0100000000000000;
                2:Y=16'b0010000000000000;
                3:Y=16'b0001000000000000;
                4:Y=16'b0000100000000000;
                5:Y=16'b0000010000000000;
                6:Y=16'b0000001000000000;
                7:Y=16'b0000000100000000;
                8:Y=16'b0000000010000000;
                9:Y=16'b0000000001000000;
                10:Y=16'b000000000100000;
                11:Y=16'b000000000010000;
                12:Y=16'b000000000001000;
                13:Y=16'b000000000000100;
                14:Y=16'b000000000000010;
                15:Y=16'b000000000000001;
            endcase
    end
endmodule

sem3/DSDL-LAB/Lab-06/q1_tb.v
`timescale 1ns/1ns
`include "q1.v"

module q1_tb();
reg [3:0] W;
// reg En;
wire F;
q1 s1(W,F);
initial
begin
$dumpfile("q1_tb.vcd");
$dumpvars(0, q1_tb);
W = 0; #20;
W = 1; #20;
W = 2; #20;
W = 3; #20;
W = 4; #20;
W = 5; #20;
W = 6; #20;
W = 7; #20;
W = 8; #20;
W = 9; #20;
W = 10; #20;
W = 11; #20;
W = 12; #20;
W = 13; #20;
W = 14; #20;
W = 15; #20;

$display("Test complete");
end
endmodule

sem3/DSDL-LAB/Lab-06/q1_tb.vcd
$date
	Sat Oct  8 16:49:25 2022
$end
$version
	Icarus Verilog
$end
$timescale
	1ns
$end
$scope module q1_tb $end
$var wire 1 ! F $end
$var reg 4 " W [3:0] $end
$scope module s1 $end
$var wire 1 ! F $end
$var wire 4 # W [3:0] $end
$var wire 16 $ Y [0:15] $end
$scope module dec $end
$var wire 4 % W [3:0] $end
$var reg 16 & Y [15:0] $end
$upscope $end
$upscope $end
$upscope $end
$enddefinitions $end
#0
$dumpvars
b1000000000000000 &
b0 %
b1000000000000000 $
b0 #
b0 "
0!
$end
#20
1!
b100000000000000 $
b100000000000000 &
b1 "
b1 #
b1 %
#40
0!
b10000000000000 $
b10000000000000 &
b10 "
b10 #
b10 %
#60
1!
b1000000000000 $
b1000000000000 &
b11 "
b11 #
b11 %
#80
0!
b100000000000 $
b100000000000 &
b100 "
b100 #
b100 %
#100
b10000000000 $
b10000000000 &
b101 "
b101 #
b101 %
#120
1!
b1000000000 $
b1000000000 &
b110 "
b110 #
b110 %
#140
b100000000 $
b100000000 &
b111 "
b111 #
b111 %
#160
0!
b10000000 $
b10000000 &
b1000 "
b1000 #
b1000 %
#180
1!
b1000000 $
b1000000 &
b1001 "
b1001 #
b1001 %
#200
0!
b100000 $
b100000 &
b1010 "
b1010 #
b1010 %
#220
b10000 $
b10000 &
b1011 "
b1011 #
b1011 %
#240
b1000 $
b1000 &
b1100 "
b1100 #
b1100 %
#260
b100 $
b100 &
b1101 "
b1101 #
b1101 %
#280
1!
b10 $
b10 &
b1110 "
b1110 #
b1110 %
#300
b1 $
b1 &
b1111 "
b1111 #
b1111 %
