sem3/DSDL-LAB/Lab-03/Q2/part1/k21.v
module k21(b,c,d,f);
    input b,c,d;
    output f;
    assign f = (~b|d)&(b|c);
endmodule

sem3/DSDL-LAB/Lab-03/Q2/part1/k21_tb.v
`timescale 1ns/1ns
`include "k21.v" 

module k2_tb();
reg b,c,d;
wire f;
k21 K21(b,c,d,f); 
initial
begin
$dumpfile("k21_tb.vcd");
$dumpvars(0, k2_tb);

b=1'b0; c=1'b0; d=1'b0; 
#20;
b=1'b0; c=1'b0; d=1'b1; 
#20;
b=1'b0; c=1'b1; d=1'b0; 
#20;
b=1'b0; c=1'b1; d=1'b1; 
#20;
b=1'b1; c=1'b0; d=1'b0; 
#20;
b=1'b1; c=1'b0; d=1'b1; 
#20;
b=1'b1; c=1'b1; d=1'b0; 
#20;
b=1'b1; c=1'b1; d=1'b1; 
#20;

$display("Test complete");
end
endmodule

sem3/DSDL-LAB/Lab-03/Q2/part1/k21_tb.vcd
$date
	Sat Sep 10 15:40:55 2022
$end
$version
	Icarus Verilog
$end
$timescale
	1ns
$end
$scope module k2_tb $end
$var wire 1 ! f $end
$var reg 1 " b $end
$var reg 1 # c $end
$var reg 1 $ d $end
$scope module K21 $end
$var wire 1 " b $end
$var wire 1 # c $end
$var wire 1 $ d $end
$var wire 1 ! f $end
$upscope $end
$upscope $end
$enddefinitions $end
#0
$dumpvars
0$
0#
0"
0!
$end
#20
1$
#40
1!
0$
1#
#60
1$
#80
0!
0$
0#
1"
#100
1!
1$
#120
0!
0$
1#
#140
1!
1$
