sem3/DSDL-LAB/Lab-01/example/example2.v
module example2(x1,x2,x3,f);
	input x1,x2,x3;
	output f;
	and(g,x1,x2);
	not(k,x2);
	and(h,k,x3);
	or(f,g,h);
endmodule

sem3/DSDL-LAB/Lab-01/example/example2_tb.v
`timescale 1ns/1ns
`include "example2.v" //Name of the Verilog file

module example2_tb();

reg x1, x2, x3;
wire f;
//Input
//Output
example2 ex2(x1, x2, x3, f); //Instantiation of the module
initial
begin
$dumpfile("example2_tb.vcd");
$dumpvars(0, example2_tb);
x1=1'b0; x2=1'b0; x3=1'b0;
#20;
x1=1'b0; x2=1'b0; x3=1'b1;
#20;
x1=1'b0; x2=1'b1; x3=1'b0;
#20;
x1=1'b0; x2=1'b1; x3=1'b1;
#20;
x1=1'b1; x2=1'b0; x3=1'b0;
#20;
x1=1'b1; x2=1'b0; x3=1'b1;
#20;
x1=1'b1; x2=1'b1; x3=1'b0;
#20;
x1=1'b1; x2=1'b1; x3=1'b1;
#20;
$display("Test complete");
end
endmodule

sem3/DSDL-LAB/Lab-01/example/example2_tb.vcd
$date
	Sat Aug 27 15:04:51 2022
$end
$version
	Icarus Verilog
$end
$timescale
	1ns
$end
$scope module example2_tb $end
$var wire 1 ! f $end
$var reg 1 " x1 $end
$var reg 1 # x2 $end
$var reg 1 $ x3 $end
$scope module ex2 $end
$var wire 1 ! f $end
$var wire 1 % g $end
$var wire 1 & h $end
$var wire 1 ' k $end
$var wire 1 " x1 $end
$var wire 1 # x2 $end
$var wire 1 $ x3 $end
$upscope $end
$upscope $end
$enddefinitions $end
#0
$dumpvars
1'
0&
0%
0$
0#
0"
0!
$end
#20
1!
1&
1$
#40
0!
0&
0'
0$
1#
#60
1$
#80
1'
0$
0#
1"
#100
1!
1&
1$
#120
0&
1%
0'
0$
1#
#140
1$
