sem3/DSDL-LAB/Lab-04/Q2/k42.v
module k42(a,b,c,d,f);
	input a,b,c,d;
	output f;
	
	nor(l,b,c);
	nor(m,b,d);
	nor(D,d,d);
	nor(n,a,c,D);
	nor(y,l,m,n);
	nor(f,y,y);
	
	//Correct answer:
	//assign f = ((~b & ~d) | (~b & ~c) | (~a & ~c & d));

endmodule

sem3/DSDL-LAB/Lab-04/Q2/k42_tb.v
`timescale 1ns/1ns
`include "k42.v" 

module k42_tb();
reg a,b,c,d;
wire f;

k42 K42(a,b,c,d,f);
initial 
begin

	$dumpfile("k42_tb.vcd");
	$dumpvars(0,k42_tb);	
	a=1'b0; b=1'b0; c=1'b0; d=1'b0;
	#20;	
	a=1'b0; b=1'b0; c=1'b0; d=1'b1;
	#20;	
	a=1'b0; b=1'b0; c=1'b1; d=1'b0;
	#20;	
	a=1'b0; b=1'b0; c=1'b1; d=1'b1;
	#20;	
	a=1'b0; b=1'b1; c=1'b0; d=1'b0;
	#20;	
	a=1'b0; b=1'b1; c=1'b0; d=1'b1;
	#20;	
	a=1'b0; b=1'b1; c=1'b1; d=1'b0;
	#20;	
	a=1'b0; b=1'b1; c=1'b1; d=1'b1;
	#20;
	a=1'b1; b=1'b0; c=1'b0; d=1'b0;
	#20;	
	a=1'b1; b=1'b0; c=1'b0; d=1'b1;
	#20;	
	a=1'b1; b=1'b0; c=1'b1; d=1'b0;
	#20;	
	a=1'b1; b=1'b0; c=1'b1; d=1'b1;
	#20;	
	a=1'b1; b=1'b1; c=1'b0; d=1'b0;
	#20;	
	a=1'b1; b=1'b1; c=1'b0; d=1'b1;
	#20;	
	a=1'b1; b=1'b1; c=1'b1; d=1'b0;
	#20;	
	a=1'b1; b=1'b1; c=1'b1; d=1'b1;
	#20;
	$display("Test Complete");
end

endmodule

sem3/DSDL-LAB/Lab-04/Q2/k42_tb.vcd
$date
	Sat Sep 17 16:43:51 2022
$end
$version
	Icarus Verilog
$end
$timescale
	1ns
$end
$scope module k42_tb $end
$var wire 1 ! f $end
$var reg 1 " a $end
$var reg 1 # b $end
$var reg 1 $ c $end
$var reg 1 % d $end
$scope module K42 $end
$var wire 1 & D $end
$var wire 1 " a $end
$var wire 1 # b $end
$var wire 1 $ c $end
$var wire 1 % d $end
$var wire 1 ! f $end
$var wire 1 ' l $end
$var wire 1 ( m $end
$var wire 1 ) n $end
$var wire 1 * y $end
$upscope $end
$upscope $end
$enddefinitions $end
#0
$dumpvars
0*
0)
1(
1'
1&
0%
0$
0#
0"
1!
$end
#20
1)
0(
0&
1%
#40
1(
1&
0'
0)
0%
1$
#60
0!
1*
0(
0&
1%
#80
0!
1*
1&
0)
0%
0$
1#
#100
1!
0*
1)
0&
1%
#120
0!
1*
1&
0)
0%
1$
#140
0&
1%
#160
1!
0*
1&
1'
1(
0%
0$
0#
1"
#180
0(
0&
1%
#200
1(
1&
0'
0%
1$
#220
0!
1*
0(
0&
1%
#240
1&
0%
0$
1#
#260
0&
1%
#280
1&
0%
1$
#300
0&
1%
