sem3/DSDL-LAB/Lab-02/Q1/q3/q3.v
module q3(x,y,z,lhs,rhs);
    input x,y,z;
    output lhs,rhs;
    assign lhs = x|(y&z);
    assign rhs = (x|y) & (x|z);
endmodule

sem3/DSDL-LAB/Lab-02/Q1/q3/q3_tb.v
`timescale 1ns/1ns
`include "q3.v" 

module q3_tb();
reg x,y,z;
wire lhs,rhs;
q3 q_3(x,y,z,lhs,rhs); 
initial
begin
$dumpfile("q3_tb.vcd");
$dumpvars(0, q3_tb);

x=1'b0; y=1'b0; z=1'b0;
#20;
x=1'b0; y=1'b0; z=1'b1;
#20;
x=1'b0; y=1'b1; z=1'b0;
#20;
x=1'b0; y=1'b1; z=1'b1;
#20;
x=1'b1; y=1'b0; z=1'b0;
#20;
x=1'b1; y=1'b0; z=1'b1;
#20;
x=1'b1; y=1'b1; z=1'b0;
#20;
x=1'b1; y=1'b1; z=1'b1;
#20;


$display("Test complete");
end
endmodule

sem3/DSDL-LAB/Lab-02/Q1/q3/q3_tb.vcd
$date
	Sat Sep  3 14:56:57 2022
$end
$version
	Icarus Verilog
$end
$timescale
	1ns
$end
$scope module q3_tb $end
$var wire 1 ! rhs $end
$var wire 1 " lhs $end
$var reg 1 # x $end
$var reg 1 $ y $end
$var reg 1 % z $end
$scope module q_3 $end
$var wire 1 " lhs $end
$var wire 1 ! rhs $end
$var wire 1 # x $end
$var wire 1 $ y $end
$var wire 1 % z $end
$upscope $end
$upscope $end
$enddefinitions $end
#0
$dumpvars
0%
0$
0#
0"
0!
$end
#20
1%
#40
0%
1$
#60
1"
1!
1%
#80
0%
0$
1#
#100
1%
#120
0%
1$
#140
1%
