sem3/DSDL-LAB/Lab-02/Q2/q1/part2/not_and.v
module not_and(a,b,c,lhs);
    input a,b,c;
    output lhs;
    assign lhs = ~(~(a&b) & ~(a&c) & ~(b&c));
endmodule

sem3/DSDL-LAB/Lab-02/Q2/q1/part2/not_and_tb.v
`timescale 1ns/1ns
`include "not_and.v" 

module not_and_tb();
reg a,b,c;
wire lhs;
not_and no_and(a,b,c,lhs); 
initial
begin
$dumpfile("not_and_tb.vcd");
$dumpvars(0, not_and_tb);

a=1'b0; b=1'b0; c=1'b0;
#20;
a=1'b0; b=1'b0; c=1'b1;
#20;
a=1'b0; b=1'b1; c=1'b0;
#20;
a=1'b0; b=1'b1; c=1'b1;
#20;
a=1'b1; b=1'b0; c=1'b0;
#20;
a=1'b1; b=1'b0; c=1'b1;
#20;
a=1'b1; b=1'b1; c=1'b0;
#20;
a=1'b1; b=1'b1; c=1'b1;
#20;



$display("Test complete");
end
endmodule

sem3/DSDL-LAB/Lab-02/Q2/q1/part2/not_and_tb.vcd
$date
	Sat Sep  3 15:39:13 2022
$end
$version
	Icarus Verilog
$end
$timescale
	1ns
$end
$scope module not_and_tb $end
$var wire 1 ! lhs $end
$var reg 1 " a $end
$var reg 1 # b $end
$var reg 1 $ c $end
$scope module no_and $end
$var wire 1 " a $end
$var wire 1 # b $end
$var wire 1 $ c $end
$var wire 1 ! lhs $end
$upscope $end
$upscope $end
$enddefinitions $end
#0
$dumpvars
0$
0#
0"
0!
$end
#20
1$
#40
0$
1#
#60
1!
1$
#80
0!
0$
0#
1"
#100
1!
1$
#120
0$
1#
#140
1$
