sem3/DSDL-LAB/Lab-03/Q2/part2/k22.v
module k22(a,b,c,d,f);
    input a,b,c,d;
    output f;
    assign f = ((~a | b | ~d) & (~a | b | ~c) & (a | ~c | d) & (~b | c | d));
endmodule

sem3/DSDL-LAB/Lab-03/Q2/part2/k22_tb.v
`timescale 1ns/1ns
`include "k22.v"

module k22_tb();
reg a,b,c,d;
wire f;
k22 K22(a,b,c,d,f); 
initial
begin
$dumpfile("k22_tb.vcd");
$dumpvars(0, k22_tb);

a=1'b0; b=1'b0; c=1'b0; d=1'b0;
#20;
a=1'b0; b=1'b0; c=1'b0; d=1'b1;
#20;
a=1'b0; b=1'b0; c=1'b1; d=1'b0;
#20;
a=1'b0; b=1'b0; c=1'b1; d=1'b1;
#20;
a=1'b0; b=1'b1; c=1'b0; d=1'b0;
#20;
a=1'b0; b=1'b1; c=1'b0; d=1'b1;
#20;
a=1'b0; b=1'b1; c=1'b1; d=1'b0;
#20;
a=1'b0; b=1'b1; c=1'b1; d=1'b1;
#20;
a=1'b1; b=1'b0; c=1'b0; d=1'b0;
#20;
a=1'b1; b=1'b0; c=1'b0; d=1'b1;
#20;
a=1'b1; b=1'b0; c=1'b1; d=1'b0;
#20;
a=1'b1; b=1'b0; c=1'b1; d=1'b1;
#20;
a=1'b1; b=1'b1; c=1'b0; d=1'b0;
#20;
a=1'b1; b=1'b1; c=1'b0; d=1'b1;
#20;
a=1'b1; b=1'b1; c=1'b1; d=1'b0;
#20;
a=1'b1; b=1'b1; c=1'b1; d=1'b1;
#20;



$display("Test complete");
end
endmodule

sem3/DSDL-LAB/Lab-03/Q2/part2/k22_tb.vcd
$date
	Sat Sep 10 15:46:33 2022
$end
$version
	Icarus Verilog
$end
$timescale
	1ns
$end
$scope module k22_tb $end
$var wire 1 ! f $end
$var reg 1 " a $end
$var reg 1 # b $end
$var reg 1 $ c $end
$var reg 1 % d $end
$scope module K22 $end
$var wire 1 " a $end
$var wire 1 # b $end
$var wire 1 $ c $end
$var wire 1 % d $end
$var wire 1 ! f $end
$upscope $end
$upscope $end
$enddefinitions $end
#0
$dumpvars
0%
0$
0#
0"
1!
$end
#20
1%
#40
0!
0%
1$
#60
1!
1%
#80
0!
0%
0$
1#
#100
1!
1%
#120
0!
0%
1$
#140
1!
1%
#160
0%
0$
0#
1"
#180
0!
1%
#200
0%
1$
#220
1%
#240
0%
0$
1#
#260
1!
1%
#280
0%
1$
#300
1%
