sem3/DSDL-LAB/Lab-05/d51.v
module d51(en,w,y);
input [1:0]en,w;
output reg [3:0]y;
always @(en,w) 
begin
    if(en==0)
    y=0;
    else
    begin
      if(w==0)
      y=1;
      else if(w==1)
      y=2;
      else if(w==2)
      y=4;
      else
      y=8;
    end    
end
endmodule

sem3/DSDL-LAB/Lab-05/d511.v
`include "d51.v"
module d511(input [2:0]w, output reg [7:0]y);

d51 s1(w[1:0],~w[2],y[3:0]);
d51 s2(w[1:0],w[2],y[7:4]);

endmodule

sem3/DSDL-LAB/Lab-05/d511_tb.v
`timescale 1ns/1ns
`include "d511.v"
module d511_tb();
reg [1:0]w;
// reg [1:0]en;
wire [7:0]y;
d511 d2to4(w,y);
    initial
    begin
    $dumpfile("d511_tb.vcd");
    $dumpvars(0, d511_tb);
    w = 3'b000; #20;
    w = 3'b001; #20;
    w = 3'b010; #20;
    w = 3'b011; #20;
    w = 3'b100; #20;
    w = 3'b101; #20;
    w = 3'b110; #20;
    w = 3'b111; #20;
$display("Test complete");
end
endmodule

sem3/DSDL-LAB/Lab-05/d511_tb.vcd
$date
	Sat Oct  1 16:24:45 2022
$end
$version
	Icarus Verilog
$end
$timescale
	1ns
$end
$scope module d511_tb $end
$var wire 8 ! y [7:0] $end
$var reg 2 " w [1:0] $end
$scope module d2to4 $end
$var wire 3 # w [2:0] $end
$var wire 8 $ y [7:0] $end
$scope module s1 $end
$var wire 2 % en [1:0] $end
$var wire 2 & w [1:0] $end
$var reg 4 ' y [3:0] $end
$upscope $end
$scope module s2 $end
$var wire 2 ( en [1:0] $end
$var wire 2 ) w [1:0] $end
$var reg 4 * y [3:0] $end
$upscope $end
$upscope $end
$upscope $end
$enddefinitions $end
#0
$dumpvars
b0 *
b0 )
b0 (
b0 '
b1 &
b0 %
b0 $
b0 #
b0 "
b0 !
$end
#20
b10 '
b10010 !
b10010 $
b1 *
b1 %
b1 (
b1 #
b1 "
#40
b10 %
b10 (
b10 #
b10 "
#60
b11 %
b11 (
b11 #
b11 "
#80
b0 '
b0 !
b0 $
b0 *
b0 %
b0 (
b0 #
b0 "
#100
b10 '
b10010 !
b10010 $
b1 *
b1 %
b1 (
b1 #
b1 "
#120
b10 %
b10 (
b10 #
b10 "
#140
b11 %
b11 (
b11 #
b11 "
