sem3/DSDL-LAB/Lab-04/Q1/k41.v
module k41(a,b,c,d,f);
    input a,b,c,d;
    output f;

    nand(B,b,b);
    nand(l,B,a);
    nand(D,d,d);
    nand(m,D,c);
    nand(n,l,m);
    nand(f,n,n);

    //assign f = ((a ~& (b ~& b)) ~& (c ~& (d ~& d))) ~& ((a ~& (b ~& b)) ~& (c ~& (d ~& d))) ;
endmodule

sem3/DSDL-LAB/Lab-04/Q1/k41_tb.v
`timescale 1ns/1ns
`include "k41.v" 

module k41_tb();
reg a,b,c,d;
wire f;

k41 K41(a,b,c,d,f);
initial 
begin

	$dumpfile("k41_tb.vcd");
	$dumpvars(0,k41_tb);	
	a=1'b0; b=1'b0; c=1'b0; d=1'b0;
	#20;	
	a=1'b0; b=1'b0; c=1'b0; d=1'b1;
	#20;	
	a=1'b0; b=1'b0; c=1'b1; d=1'b0;
	#20;	
	a=1'b0; b=1'b0; c=1'b1; d=1'b1;
	#20;	
	a=1'b0; b=1'b1; c=1'b0; d=1'b0;
	#20;	
	a=1'b0; b=1'b1; c=1'b0; d=1'b1;
	#20;	
	a=1'b0; b=1'b1; c=1'b1; d=1'b0;
	#20;	
	a=1'b0; b=1'b1; c=1'b1; d=1'b1;
	#20;	
	a=1'b1; b=1'b0; c=1'b0; d=1'b0;
	#20;	
	a=1'b1; b=1'b0; c=1'b0; d=1'b1;
	#20;	
	a=1'b1; b=1'b0; c=1'b1; d=1'b0;
	#20;	
	a=1'b1; b=1'b0; c=1'b1; d=1'b1;
	#20;	
	a=1'b1; b=1'b1; c=1'b0; d=1'b0;
	#20;	
	a=1'b1; b=1'b1; c=1'b0; d=1'b1;
	#20;	
	a=1'b1; b=1'b1; c=1'b1; d=1'b0;
	#20;	
	a=1'b1; b=1'b1; c=1'b1; d=1'b1;
	#20;
	$display("Test Complete");
end

endmodule

sem3/DSDL-LAB/Lab-04/Q1/k41_tb.vcd
$date
	Sat Sep 17 16:35:36 2022
$end
$version
	Icarus Verilog
$end
$timescale
	1ns
$end
$scope module k41_tb $end
$var wire 1 ! f $end
$var reg 1 " a $end
$var reg 1 # b $end
$var reg 1 $ c $end
$var reg 1 % d $end
$scope module K41 $end
$var wire 1 & B $end
$var wire 1 ' D $end
$var wire 1 " a $end
$var wire 1 # b $end
$var wire 1 $ c $end
$var wire 1 % d $end
$var wire 1 ! f $end
$var wire 1 ( l $end
$var wire 1 ) m $end
$var wire 1 * n $end
$upscope $end
$upscope $end
$enddefinitions $end
#0
$dumpvars
0*
1)
1(
1'
1&
0%
0$
0#
0"
1!
$end
#20
0'
1%
#40
0!
1*
0)
1'
0%
1$
#60
1!
0*
1)
0'
1%
#80
1'
0&
0%
0$
1#
#100
0'
1%
#120
0!
1*
0)
1'
0%
1$
#140
1!
0*
1)
0'
1%
#160
0!
1*
0(
1'
1&
0%
0$
0#
1"
#180
0'
1%
#200
0)
1'
0%
1$
#220
1)
0'
1%
#240
1!
0*
1(
1'
0&
0%
0$
1#
#260
0'
1%
#280
0!
1*
0)
1'
0%
1$
#300
1!
0*
1)
0'
1%
