sem3/DSDL-LAB/Lab-03/Q3/k3.v
module k3(x1,x2,x3,x4,f);
	input x1,x2,x3,x4;
	output f;	
	assign f = ((x4 & x1 & x2) | (x3 & x1 & x2) | (x1 & x3 & x4) | (x2 & x3 & x4));	
endmodule

sem3/DSDL-LAB/Lab-03/Q3/k3_tb.v
`timescale 1ns/1ns
`include "k3.v"

module k3_tb();
reg a,b,c,d;
wire f;
k3 K3(a,b,c,d,f); 
initial
begin
$dumpfile("k3_tb.vcd");
$dumpvars(0, k3_tb);

a=1'b0; b=1'b0; c=1'b0; d=1'b0;
#20;
a=1'b0; b=1'b0; c=1'b0; d=1'b1;
#20;
a=1'b0; b=1'b0; c=1'b1; d=1'b0;
#20;
a=1'b0; b=1'b0; c=1'b1; d=1'b1;
#20;
a=1'b0; b=1'b1; c=1'b0; d=1'b0;
#20;
a=1'b0; b=1'b1; c=1'b0; d=1'b1;
#20;
a=1'b0; b=1'b1; c=1'b1; d=1'b0;
#20;
a=1'b0; b=1'b1; c=1'b1; d=1'b1;
#20;
a=1'b1; b=1'b0; c=1'b0; d=1'b0;
#20;
a=1'b1; b=1'b0; c=1'b0; d=1'b1;
#20;
a=1'b1; b=1'b0; c=1'b1; d=1'b0;
#20;
a=1'b1; b=1'b0; c=1'b1; d=1'b1;
#20;
a=1'b1; b=1'b1; c=1'b0; d=1'b0;
#20;
a=1'b1; b=1'b1; c=1'b0; d=1'b1;
#20;
a=1'b1; b=1'b1; c=1'b1; d=1'b0;
#20;
a=1'b1; b=1'b1; c=1'b1; d=1'b1;
#20;



$display("Test complete");
end
endmodule

sem3/DSDL-LAB/Lab-03/Q3/k3_tb.vcd
$date
	Sat Sep 10 15:54:47 2022
$end
$version
	Icarus Verilog
$end
$timescale
	1ns
$end
$scope module k3_tb $end
$var wire 1 ! f $end
$var reg 1 " a $end
$var reg 1 # b $end
$var reg 1 $ c $end
$var reg 1 % d $end
$scope module K3 $end
$var wire 1 ! f $end
$var wire 1 " x1 $end
$var wire 1 # x2 $end
$var wire 1 $ x3 $end
$var wire 1 % x4 $end
$upscope $end
$upscope $end
$enddefinitions $end
#0
$dumpvars
0%
0$
0#
0"
0!
$end
#20
1%
#40
0%
1$
#60
1%
#80
0%
0$
1#
#100
1%
#120
0%
1$
#140
1!
1%
#160
0!
0%
0$
0#
1"
#180
1%
#200
0%
1$
#220
1!
1%
#240
0!
0%
0$
1#
#260
1!
1%
#280
0%
1$
#300
1%
